tt_damage_calculator-4.3.2.dist-info/METADATA
tt_damage_calculator-4.3.2.dist-info/WHEEL
tt_damage_calculator-4.3.2.dist-info/entry_points.txt
tt_damage_calculator-4.3.2.dist-info/license_files/LICENSE
tt_damage_calculator.libs/libcrypto-a50d99cb.so.3
tt_damage_calculator.libs/libssl-91d34894.so.3
tt_damage_calculator/Toontown Damage Calculator.py
tt_damage_calculator/__main__.py
tt_damage_calculator/widgets.py
tt_damage_calculator/assets/settings.toml
tt_damage_calculator/assets/version.txt
tt_damage_calculator/assets/img/grand-piano.png
tt_damage_calculator/assets/img/squirt-gun.png
tt_damage_calculator/assets/img/coghp.png
tt_damage_calculator/assets/img/whistle.png
tt_damage_calculator/assets/img/sandbag.png
tt_damage_calculator/assets/img/banana-peel.png
tt_damage_calculator/assets/img/railroad.png
tt_damage_calculator/assets/img/toontanic.png
tt_damage_calculator/assets/img/franzneckvein.png
tt_damage_calculator/assets/img/wedding-cake.png
tt_damage_calculator/assets/img/bike-horn.png
tt_damage_calculator/assets/img/clumsyned.png
tt_damage_calculator/assets/img/storm-cloud.png
tt_damage_calculator/assets/img/flower-pot.png
tt_damage_calculator/assets/img/squirting-flower.png
tt_damage_calculator/assets/img/cupcake.png
tt_damage_calculator/assets/img/bugle.png
tt_damage_calculator/assets/img/barnaclebessie.png
tt_damage_calculator/assets/img/sidsonata.png
tt_damage_calculator/assets/img/marbles.png
tt_damage_calculator/assets/img/opera-singer.png
tt_damage_calculator/assets/img/clerkpenny.png
tt_damage_calculator/assets/img/quicksand.png
tt_damage_calculator/assets/img/whole-cream-pie.ico
tt_damage_calculator/assets/img/cream-pie-slice.png
tt_damage_calculator/assets/img/whole-cream-pie.png
tt_damage_calculator/assets/img/anvil.png
tt_damage_calculator/assets/img/fire-hose.png
tt_damage_calculator/assets/img/whole-fruit-pie.png
tt_damage_calculator/assets/img/fruit-pie-slice.png
tt_damage_calculator/assets/img/birthday-cake.png
tt_damage_calculator/assets/img/big-weight.png
tt_damage_calculator/assets/img/aoogah.png
tt_damage_calculator/assets/img/rake.png
tt_damage_calculator/assets/img/clerkclara.png
tt_damage_calculator/assets/img/moezart.png
tt_damage_calculator-4.3.2.dist-info/RECORD
