Metadata-Version: 2.3
Name: tt_damage_calculator
Version: 4.3.2
Classifier: Programming Language :: Python :: 3
Classifier: License :: OSI Approved :: GNU General Public License v3 (GPLv3)
Classifier: Operating System :: OS Independent
License-File: LICENSE
Summary: A Python binary package that will help you calculate gag combinations on the fly!
Author: Vhou-Atroph
Author-email: Vhou-Atroph <vhouatroph@proton.me>
License: GPLv3
Requires-Python: >=3.11
Project-URL: Homepage, https://vhou.gloop.group/projects/gagcalc
Project-URL: Repository, https://github.com/Vhou-Atroph/TT-Damage-Calculator
Project-URL: Bug Tracker, https://github.com/Vhou-Atroph/TT-Damage-Calculator/issues
